todo_sync/__init__.py
todo_sync/command_line.py
todo_sync/edit_script.py
todo_sync/helpers.py
todo_sync/node.py
todo_sync/source.py
todo_sync/backends/__init__.py
todo_sync/backends/asana.py
todo_sync/backends/org.py
todo_sync/mappers/__init__.py
todo_sync/mappers/asana_to_org.py
todo_sync/mappers/org_to_asana.py
todo_sync-0.3.1.dist-info/METADATA
todo_sync-0.3.1.dist-info/RECORD
todo_sync-0.3.1.dist-info/WHEEL
todo_sync-0.3.1.dist-info/entry_points.txt
todo_sync-0.3.1.dist-info/top_level.txt
