Metadata-Version: 2.1
Name: todo-sync
Version: 0.3.1
Summary: Synchronize todo lists, supports Emacs Org Mode and Asana.
Home-page: https://github.com/tmurph/todo-sync
Author: Trevor Murphy
Author-email: trevor.m.murphy@gmail.com
License: GPL3
Platform: UNKNOWN
Classifier: Development Status :: 3 - Alpha
Classifier: License :: OSI Approved :: GNU General Public License v3 or later (GPLv3+)
Classifier: Programming Language :: Python :: 3.6
Classifier: Topic :: Utilities
Requires-Python: >=3, <3.7
Requires-Dist: asana
Requires-Dist: pexpect (>=4.3)
